pylandau.cp310-win_amd64.pyd
pyLandau/__init__.py
pyLandau/cpp/pylandau.cpp
pyLandau/cpp/pylandau.pyx
pyLandau/cpp/pylandau_src.cpp
tests/__init__.py
tests/constraints.py
tests/test_data_types.py
tests/test_exceptions.py
tests/test_fuzzing.py
tests/test_properties.py
tests/__pycache__/__init__.cpython-38.pyc
tests/__pycache__/__init__.cpython-39.pyc
tests/__pycache__/constraints.cpython-38.pyc
tests/__pycache__/constraints.cpython-39.pyc
tests/__pycache__/test_data_types.cpython-38-pytest-7.1.2.pyc
tests/__pycache__/test_data_types.cpython-39-pytest-7.1.2.pyc
tests/__pycache__/test_exceptions.cpython-38-pytest-7.1.2.pyc
tests/__pycache__/test_exceptions.cpython-39-pytest-7.1.2.pyc
tests/__pycache__/test_fuzzing.cpython-38-pytest-7.1.2.pyc
tests/__pycache__/test_fuzzing.cpython-39-pytest-7.1.2.pyc
tests/__pycache__/test_properties.cpython-38-pytest-7.1.2.pyc
tests/__pycache__/test_properties.cpython-39-pytest-7.1.2.pyc
pylandau-2.2.1.dist-info/LICENSE
pylandau-2.2.1.dist-info/METADATA
pylandau-2.2.1.dist-info/WHEEL
pylandau-2.2.1.dist-info/top_level.txt
pylandau-2.2.1.dist-info/RECORD
