Metadata-Version: 2.1
Name: pylandau
Version: 2.2.1
Summary: A Landau PDF definition to be used in Python.
Author-email: David-Leon Pohl <pohl@physik.uni-bonn.de>, Christian Bespin <bespin@physik.uni-bonn.de>
Maintainer-email: Christian Bespin <bespin@physik.uni-bonn.de>
License:                   GNU LESSER GENERAL PUBLIC LICENSE
Project-URL: repository, https://github.com/SiLab-Bonn/pyLandau
Keywords: Landau,Langau,PDF
Platform: any
Requires-Python: >=3.8
License-File: LICENSE
